sector8/__init__.py
sector8/config_wizard.py
sector8/errors.py
sector8/py.typed
sector8/simple_client.py
sector8_sdk-1.0.0.dist-info/licenses/LICENSE
sector8_sdk-1.0.0.dist-info/METADATA
sector8_sdk-1.0.0.dist-info/WHEEL
sector8_sdk-1.0.0.dist-info/entry_points.txt
sector8_sdk-1.0.0.dist-info/top_level.txt
sector8_sdk-1.0.0.dist-info/RECORD
