Metadata-Version: 2.4
Name: sector8-sdk
Version: 1.0.0
Summary: Enterprise AI Security, Observability, and Intelligence SDK
Author-email: Sector8 Team <support@sector8.ai>
Maintainer-email: Sector8 Team <support@sector8.ai>
License: MIT
Project-URL: Homepage, https://sector8.ai
Project-URL: Documentation, https://docs.sector8.ai
Project-URL: Repository, https://github.com/sector8-labs/sector8-python-sdk
Project-URL: Bug Tracker, https://github.com/sector8-labs/sector8-python-sdk/issues
Project-URL: Source Code, https://github.com/sector8-labs/sector8-python-sdk
Project-URL: Security Policy, https://github.com/sector8-labs/sector8-python-sdk/security/policy
Keywords: ai,security,observability,intelligence,llm,telemetry,monitoring
Classifier: Development Status :: 5 - Production/Stable
Classifier: Intended Audience :: Developers
Classifier: License :: OSI Approved :: MIT License
Classifier: Operating System :: OS Independent
Classifier: Programming Language :: Python :: 3
Classifier: Programming Language :: Python :: 3.8
Classifier: Programming Language :: Python :: 3.9
Classifier: Programming Language :: Python :: 3.10
Classifier: Programming Language :: Python :: 3.11
Classifier: Programming Language :: Python :: 3.12
Classifier: Topic :: Software Development :: Libraries :: Python Modules
Classifier: Topic :: Security
Classifier: Topic :: System :: Monitoring
Classifier: Topic :: Scientific/Engineering :: Artificial Intelligence
Requires-Python: >=3.8
License-File: LICENSE
Requires-Dist: aiohttp>=3.8.0
Requires-Dist: pydantic>=2.0.0
Requires-Dist: click>=8.0.0
Requires-Dist: rich>=13.0.0
Requires-Dist: asyncio-mqtt>=0.11.0
Requires-Dist: python-dotenv>=1.0.0
Requires-Dist: typing-extensions>=4.0.0
Requires-Dist: opentelemetry-api>=1.20.0
Requires-Dist: opentelemetry-sdk>=1.20.0
Requires-Dist: opentelemetry-instrumentation<1.0.0,>=0.52b0
Requires-Dist: wrapt>=1.14.0
Requires-Dist: keyring>=25.0.0
Requires-Dist: cryptography>=3.4.0
Requires-Dist: tenacity>=8.0.0
Requires-Dist: requests>=2.28.0
Provides-Extra: openai
Requires-Dist: openai>=1.0.0; extra == "openai"
Provides-Extra: anthropic
Requires-Dist: anthropic>=0.7.0; extra == "anthropic"
Provides-Extra: google
Requires-Dist: google-generativeai>=0.3.0; extra == "google"
Provides-Extra: azure
Requires-Dist: openai>=1.0.0; extra == "azure"
Provides-Extra: otel
Requires-Dist: opentelemetry-api>=1.20.0; extra == "otel"
Requires-Dist: opentelemetry-sdk>=1.20.0; extra == "otel"
Requires-Dist: opentelemetry-instrumentation<1.0.0,>=0.52b0; extra == "otel"
Requires-Dist: opentelemetry-exporter-otlp>=1.20.0; extra == "otel"
Provides-Extra: prometheus
Requires-Dist: prometheus-client>=0.17.0; extra == "prometheus"
Provides-Extra: datadog
Requires-Dist: datadog>=0.44.0; extra == "datadog"
Provides-Extra: ml
Requires-Dist: pandas>=1.5.0; extra == "ml"
Requires-Dist: numpy>=1.24.0; extra == "ml"
Requires-Dist: scikit-learn>=1.3.0; extra == "ml"
Provides-Extra: dev
Requires-Dist: pytest>=7.0.0; extra == "dev"
Requires-Dist: pytest-asyncio>=0.21.0; extra == "dev"
Requires-Dist: pytest-cov>=4.0.0; extra == "dev"
Requires-Dist: black>=23.0.0; extra == "dev"
Requires-Dist: flake8>=6.0.0; extra == "dev"
Requires-Dist: mypy>=1.0.0; extra == "dev"
Requires-Dist: pre-commit>=3.0.0; extra == "dev"
Provides-Extra: docs
Requires-Dist: sphinx>=6.0.0; extra == "docs"
Requires-Dist: sphinx-rtd-theme>=1.2.0; extra == "docs"
Requires-Dist: myst-parser>=1.0.0; extra == "docs"
Provides-Extra: all
Requires-Dist: openai>=1.0.0; extra == "all"
Requires-Dist: anthropic>=0.7.0; extra == "all"
Requires-Dist: google-generativeai>=0.3.0; extra == "all"
Requires-Dist: opentelemetry-api>=1.20.0; extra == "all"
Requires-Dist: opentelemetry-sdk>=1.20.0; extra == "all"
Requires-Dist: opentelemetry-instrumentation<1.0.0,>=0.52b0; extra == "all"
Requires-Dist: opentelemetry-exporter-otlp>=1.20.0; extra == "all"
Requires-Dist: prometheus-client>=0.17.0; extra == "all"
Requires-Dist: datadog>=0.44.0; extra == "all"
Requires-Dist: pandas>=1.5.0; extra == "all"
Requires-Dist: numpy>=1.24.0; extra == "all"
Requires-Dist: scikit-learn>=1.3.0; extra == "all"
Dynamic: license-file
